hurnet/__init__.py
hurnet/_hurnet.py
hurnet/hurnet.py
hurnet-1.0.8.dist-info/LICENSE.txt
hurnet-1.0.8.dist-info/METADATA
hurnet-1.0.8.dist-info/WHEEL
hurnet-1.0.8.dist-info/top_level.txt
hurnet-1.0.8.dist-info/RECORD
