Metadata-Version: 2.2
Name: hurnet
Version: 1.0.8
Home-page: https://github.com/sapiens-technology/HurNet
Author: SAPIENS TECHNOLOGY
License: Proprietary Software
License-File: LICENSE.txt
Requires-Dist: numpy
Dynamic: author
Dynamic: home-page
Dynamic: license
Dynamic: requires-dist
